django_nice/__init__.py
django_nice/config.py
django_nice/frontend.py
django_nice/signals.py
django_nice/sse.py
django_nice/urls.py
django_nice/views.py
django_nice-0.5.157.dist-info/LICENSE
django_nice-0.5.157.dist-info/METADATA
django_nice-0.5.157.dist-info/WHEEL
django_nice-0.5.157.dist-info/top_level.txt
django_nice-0.5.157.dist-info/RECORD
