Metadata-Version: 2.1
Name: django-nice
Version: 0.5.157
Summary: Library to bind Django models with NiceGUI elements using API and SSE.
Home-page: https://github.com/rexsum420/django-nice
Author: Jeffery Springs
Author-email: rexsum420@gmail.com
Requires-Python: >=3.6
License-File: LICENSE
Requires-Dist: Django>=3.2
Requires-Dist: django-sse
Requires-Dist: nicegui
Requires-Dist: requests
Provides-Extra: dev
Requires-Dist: pytest; extra == "dev"
Requires-Dist: black; extra == "dev"
Requires-Dist: flake8; extra == "dev"
